{
  "id": "fchollet",
  "stars": [],
  "posts": [],
  "videos": [],
  "blogs": [],
  "xPosts": [
    {
      "type": "x",
      "id": "1300137812872765440",
      "url": "https://x.com/fchollet/status/1300137812872765440",
      "author": {
        "handle": "fchollet",
        "displayName": "Francois Chollet",
        "avatar": "https://avatars.githubusercontent.com/fchollet"
      },
      "content": "I think it's clear that for many smaller companies that invested in deep learning, it turned out",
      "createdAt": "2026-04-16T11:13:58.793Z",
      "likeCount": 0,
      "replyCount": 0,
      "retweetCount": 0,
      "highlights": "Chollet suggests that deep learning investments haven't paid off for many smaller companies, implying practical limitations or misalignment with business needs.",
      "worthReading": "This offers a critical perspective on the real-world ROI of deep learning for smaller organizations.",
      "tags": [
        "evaluation",
        "deployment"
      ]
    },
    {
      "type": "x",
      "id": "1300137812872765440",
      "url": "https://x.com/fchollet/status/1300137812872765440",
      "author": {
        "handle": "fchollet",
        "displayName": "Francois Chollet",
        "avatar": "https://avatars.githubusercontent.com/fchollet"
      },
      "content": "I think it's clear that for many smaller companies that invested in deep learning, it turned out",
      "createdAt": "2026-04-16T11:13:58.793Z",
      "likeCount": 0,
      "replyCount": 0,
      "retweetCount": 0,
      "highlights": "Chollet suggests that deep learning investments haven't paid off for many smaller companies, implying practical limitations or misalignment with business needs.",
      "worthReading": "This offers a critical perspective on the real-world ROI of deep learning for smaller organizations.",
      "tags": [
        "evaluation",
        "deployment"
      ]
    },
    {
      "type": "x",
      "id": "2018836816552694139",
      "url": "https://x.com/fchollet/status/2018836816552694139",
      "author": {
        "handle": "fchollet",
        "displayName": "Francois Chollet",
        "avatar": "https://avatars.githubusercontent.com/fchollet"
      },
      "content": "Folks who work in AI or software engineering feel like the world is changing exponential fast.",
      "createdAt": "2026-04-18T04:02:21.004Z",
      "likeCount": 0,
      "replyCount": 0,
      "retweetCount": 0,
      "highlights": "AI and software engineering professionals perceive the world as changing at an exponential pace.",
      "worthReading": "Captures the rapid pace of technological change experienced by practitioners in the field.",
      "tags": [
        "agent"
      ]
    },
    {
      "type": "x",
      "id": "1690461214579806208",
      "url": "https://x.com/fchollet/status/1690461214579806208",
      "author": {
        "handle": "fchollet",
        "displayName": "Francois Chollet",
        "avatar": "https://avatars.githubusercontent.com/fchollet"
      },
      "content": "Re-reading an article I wrote in 2017, and I'm finding I could have written it yesterday.",
      "createdAt": "2026-04-18T04:02:21.004Z",
      "likeCount": 0,
      "replyCount": 0,
      "retweetCount": 0,
      "highlights": "The author finds that an article written in 2017 remains relevant and could have been written recently.",
      "worthReading": "Highlights the enduring nature of certain insights in AI and technology.",
      "tags": [
        "evaluation"
      ]
    }
  ],
  "dailyCounts": [
    0,
    0,
    0,
    0,
    0,
    0,
    0,
    0,
    0,
    0,
    0,
    0,
    0,
    0,
    0,
    0,
    0,
    0,
    0,
    0,
    0,
    0,
    0,
    0,
    0,
    1,
    1,
    0,
    0,
    2
  ],
  "interestSummary": "Their recent focus is on the practical outcomes and adoption challenges of deep learning, particularly for smaller companies, while reflecting on the perceived versus actual pace of change in AI and software engineering."
}
